cdk_valheim/__init__.py
cdk_valheim/py.typed
cdk_valheim/_jsii/__init__.py
cdk_valheim/_jsii/cdk-valheim@0.0.26.jsii.tgz
cdk_valheim-0.0.26.dist-info/LICENSE
cdk_valheim-0.0.26.dist-info/METADATA
cdk_valheim-0.0.26.dist-info/WHEEL
cdk_valheim-0.0.26.dist-info/top_level.txt
cdk_valheim-0.0.26.dist-info/RECORD
